{
  "as_of": "2026-03-10",
  "published_at": "2026-03-10 19:06:23 CET",
  "mode": "near_realtime",
  "refresh_interval_seconds": 300,
  "ui_poll_interval_seconds": 60,
  "gold": {
    "international": {
      "label": "国际金价",
      "value": 5219.74,
      "unit": "USD/oz",
      "category": "gold",
      "timestamp": "2026-03-10T19:06:23+01:00",
      "market_time": "2026-03-11 02:06:00",
      "change_abs": -7.7,
      "change_pct": -0.1473,
      "change_basis": "较上次抓取",
      "source_name": "新浪财经",
      "source_url": "https://finance.sina.com.cn/money/future/hf.html",
      "source_note": "伦敦金（现货黄金）",
      "secondary_value": null
    },
    "shanghai": {
      "label": "上海金价",
      "value": 1158.0,
      "unit": "CNY/g",
      "category": "gold",
      "timestamp": "2026-03-10T19:06:23+01:00",
      "market_time": "2026-03-10 19:06:23 CET",
      "change_abs": 0.0,
      "change_pct": 0.0,
      "change_basis": "较上次抓取",
      "source_name": "上海黄金交易所",
      "source_url": "https://www.sge.com.cn/sjzx/yshqbg",
      "source_note": "延时行情 Au99.99",
      "secondary_value": null
    }
  },
  "fx": {
    "eur_cny": {
      "label": "欧元兑人民币",
      "value": 8.0044,
      "unit": "CNY",
      "category": "fx",
      "timestamp": "2026-03-10T19:06:23+01:00",
      "market_time": "2026-03-11 02:06:16",
      "change_abs": -0.0144,
      "change_pct": -0.1796,
      "change_basis": "较上次抓取",
      "source_name": "新浪财经",
      "source_url": "https://finance.sina.com.cn/money/forex/hq/EURCNY.shtml",
      "source_note": "欧元兑人民币即期汇率",
      "secondary_value": null
    },
    "usd_cny": {
      "label": "美元兑人民币",
      "value": 6.865,
      "unit": "CNY",
      "category": "fx",
      "timestamp": "2026-03-10T19:06:23+01:00",
      "market_time": "2026-03-11 02:05:02",
      "change_abs": 0.0033,
      "change_pct": 0.0481,
      "change_basis": "较上次抓取",
      "source_name": "新浪财经",
      "source_url": "https://finance.sina.com.cn/money/forex/hq/USDCNY.shtml",
      "source_note": "美元兑人民币即期汇率",
      "secondary_value": null
    }
  },
  "crypto": {
    "btc_cny": {
      "label": "BTC 人民币价格",
      "value": 487247.0,
      "unit": "CNY",
      "category": "crypto",
      "timestamp": "2026-03-10T19:06:23+01:00",
      "market_time": "2026-03-10 19:06:23 CET",
      "change_abs": -2700.0,
      "change_pct": -0.5511,
      "change_basis": "较上次抓取",
      "source_name": "CoinGecko",
      "source_url": "https://www.coingecko.com/en/coins/bitcoin",
      "source_note": "Bitcoin spot price",
      "secondary_value": "≈ 70852.00 USD"
    },
    "btc_usd": {
      "label": "BTC 美元价格",
      "value": 70852.0,
      "unit": "USD",
      "category": "crypto",
      "timestamp": "2026-03-10T19:06:23+01:00",
      "market_time": "2026-03-10 19:06:23 CET",
      "change_abs": -392.0,
      "change_pct": -0.5502,
      "change_basis": "较上次抓取",
      "source_name": "CoinGecko",
      "source_url": "https://www.coingecko.com/en/coins/bitcoin",
      "source_note": "Bitcoin spot price",
      "secondary_value": "≈ 487247.00 CNY"
    }
  },
  "sources": [
    {
      "id": "sina_gold",
      "label": "新浪财经 伦敦金",
      "url": "https://finance.sina.com.cn/money/future/hf.html"
    },
    {
      "id": "sge",
      "label": "上海黄金交易所 延时行情 Au99.99",
      "url": "https://www.sge.com.cn/sjzx/yshqbg"
    },
    {
      "id": "sina_fx",
      "label": "新浪财经 外汇即期汇率",
      "url": "https://finance.sina.com.cn/money/forex/hq.shtml"
    },
    {
      "id": "coingecko",
      "label": "CoinGecko Bitcoin Spot",
      "url": "https://www.coingecko.com/en/coins/bitcoin"
    }
  ]
}
