{
  "as_of": "2026-04-09",
  "published_at": "2026-04-09 13:57:32 CEST",
  "mode": "near_realtime",
  "refresh_interval_seconds": 300,
  "ui_poll_interval_seconds": 60,
  "gold": {
    "international": {
      "label": "国际金价",
      "value": 4756.58,
      "unit": "USD/oz",
      "category": "gold",
      "timestamp": "2026-04-09T13:57:32+02:00",
      "market_time": "2026-04-09 19:57:00",
      "change_abs": 14.82,
      "change_pct": 0.3125,
      "change_basis": "较上次抓取",
      "source_name": "新浪财经",
      "source_url": "https://finance.sina.com.cn/money/future/hf.html",
      "source_note": "伦敦金（现货黄金）",
      "secondary_value": null
    },
    "shanghai": {
      "label": "上海金价",
      "value": 0.0,
      "unit": "CNY/g",
      "category": "gold",
      "timestamp": "2026-04-09T13:57:32+02:00",
      "market_time": "2026-04-09 13:57:32 CEST",
      "change_abs": 0.0,
      "change_pct": null,
      "change_basis": "较上次抓取",
      "source_name": "上海黄金交易所",
      "source_url": "https://www.sge.com.cn/sjzx/yshqbg",
      "source_note": "延时行情 Au99.99",
      "secondary_value": null
    }
  },
  "fx": {
    "eur_cny": {
      "label": "欧元兑人民币",
      "value": 7.9873,
      "unit": "CNY",
      "category": "fx",
      "timestamp": "2026-04-09T13:57:32+02:00",
      "market_time": "2026-04-09 19:57:21",
      "change_abs": 0.0052,
      "change_pct": 0.0651,
      "change_basis": "较上次抓取",
      "source_name": "新浪财经",
      "source_url": "https://finance.sina.com.cn/money/forex/hq/EURCNY.shtml",
      "source_note": "欧元兑人民币即期汇率",
      "secondary_value": null
    },
    "usd_cny": {
      "label": "美元兑人民币",
      "value": 6.835,
      "unit": "CNY",
      "category": "fx",
      "timestamp": "2026-04-09T13:57:32+02:00",
      "market_time": "2026-04-09 19:55:16",
      "change_abs": -0.0049,
      "change_pct": -0.0716,
      "change_basis": "较上次抓取",
      "source_name": "新浪财经",
      "source_url": "https://finance.sina.com.cn/money/forex/hq/USDCNY.shtml",
      "source_note": "美元兑人民币即期汇率",
      "secondary_value": null
    }
  },
  "crypto": {
    "btc_cny": {
      "label": "BTC 人民币价格",
      "value": 486495.0,
      "unit": "CNY",
      "category": "crypto",
      "timestamp": "2026-04-09T13:57:32+02:00",
      "market_time": "2026-04-09 13:57:32 CEST",
      "change_abs": -1246.0,
      "change_pct": -0.2555,
      "change_basis": "较上次抓取",
      "source_name": "CoinGecko",
      "source_url": "https://www.coingecko.com/en/coins/bitcoin",
      "source_note": "Bitcoin spot price",
      "secondary_value": "≈ 71169.00 USD"
    },
    "btc_usd": {
      "label": "BTC 美元价格",
      "value": 71169.0,
      "unit": "USD",
      "category": "crypto",
      "timestamp": "2026-04-09T13:57:32+02:00",
      "market_time": "2026-04-09 13:57:32 CEST",
      "change_abs": -132.0,
      "change_pct": -0.1851,
      "change_basis": "较上次抓取",
      "source_name": "CoinGecko",
      "source_url": "https://www.coingecko.com/en/coins/bitcoin",
      "source_note": "Bitcoin spot price",
      "secondary_value": "≈ 486495.00 CNY"
    }
  },
  "sources": [
    {
      "id": "sina_gold",
      "label": "新浪财经 伦敦金",
      "url": "https://finance.sina.com.cn/money/future/hf.html"
    },
    {
      "id": "sge",
      "label": "上海黄金交易所 延时行情 Au99.99",
      "url": "https://www.sge.com.cn/sjzx/yshqbg"
    },
    {
      "id": "sina_fx",
      "label": "新浪财经 外汇即期汇率",
      "url": "https://finance.sina.com.cn/money/forex/hq.shtml"
    },
    {
      "id": "coingecko",
      "label": "CoinGecko Bitcoin Spot",
      "url": "https://www.coingecko.com/en/coins/bitcoin"
    }
  ]
}
